[[{"year":2010,"quantity":173},{"year":2011,"quantity":371},{"year":2012,"quantity":641},{"year":2013,"quantity":894.7},{"year":2014,"quantity":1098},{"year":2015,"quantity":1218},{"year":2016,"quantity":1258},{"year":2017,"quantity":1313},{"year":2018,"quantity":1318},{"year":2019,"quantity":330}],[{"year":2008,"quantity":100},{"year":2009,"quantity":1104},{"year":2010,"quantity":2071},{"year":2011,"quantity":3064},{"year":2012,"quantity":3919},{"year":2013,"quantity":4682},{"year":2014,"quantity":5336},{"year":2015,"quantity":6067},{"year":2016,"quantity":7014},{"year":2017,"quantity":8143},{"year":2018,"quantity":9021},{"year":2019,"quantity":9736},{"year":2020,"quantity":10841}]]